aci_utils/__init__.py
aci_utils/aci_utils.py
aci_utils/validator_model_utils.py
aci_utils-0.0.1.dist-info/LICENSE.txt
aci_utils-0.0.1.dist-info/METADATA
aci_utils-0.0.1.dist-info/WHEEL
aci_utils-0.0.1.dist-info/top_level.txt
aci_utils-0.0.1.dist-info/RECORD
