Metadata-Version: 2.1
Name: aci-utils
Version: 0.0.1
Summary: Define una clase para interactuar con la API de Cisco ACI
Author: Endika Zuazo
Author-email: endikazuazo@gmail.com
License: MIT
Keywords: example project
Platform: UNKNOWN
License-File: LICENSE.txt
